kiara_plugin/network_analysis/__init__.py
kiara_plugin/network_analysis/data_types.py
kiara_plugin/network_analysis/defaults.py
kiara_plugin/network_analysis/py.typed
kiara_plugin/network_analysis/utils.py
kiara_plugin/network_analysis/version.txt
kiara_plugin/network_analysis/models/__init__.py
kiara_plugin/network_analysis/models/inputs.py
kiara_plugin/network_analysis/models/metadata.py
kiara_plugin/network_analysis/modules/__init__.py
kiara_plugin/network_analysis/modules/components.py
kiara_plugin/network_analysis/modules/create.py
kiara_plugin/network_analysis/modules/export.py
kiara_plugin/network_analysis/modules/filters.py
kiara_plugin/network_analysis/modules/rendering.py
kiara_plugin/network_analysis/pipelines/.gitkeep
kiara_plugin/network_analysis/pipelines/__init__.py
kiara_plugin/network_analysis/resources/.gitkeep
kiara_plugin/network_analysis/streamlit/__init__.py
kiara_plugin/network_analysis/streamlit/components/__init__.py
kiara_plugin/network_analysis/streamlit/components/data_import.py
kiara_plugin.network_analysis-0.5.1.dist-info/AUTHORS.md
kiara_plugin.network_analysis-0.5.1.dist-info/LICENSE
kiara_plugin.network_analysis-0.5.1.dist-info/METADATA
kiara_plugin.network_analysis-0.5.1.dist-info/WHEEL
kiara_plugin.network_analysis-0.5.1.dist-info/entry_points.txt
kiara_plugin.network_analysis-0.5.1.dist-info/top_level.txt
kiara_plugin.network_analysis-0.5.1.dist-info/RECORD
